dinero_auth/__init__.py
dinero_auth/admin.py
dinero_auth/apps.py
dinero_auth/auth.py
dinero_auth/crypto.py
dinero_auth/models.py
dinero_auth/tests.py
dinero_auth/token.py
dinero_auth/views.py
dinero_auth-1.0.dist-info/LICENSE
dinero_auth-1.0.dist-info/METADATA
dinero_auth-1.0.dist-info/WHEEL
dinero_auth-1.0.dist-info/top_level.txt
dinero_auth-1.0.dist-info/RECORD
